wrapping/__init__.py
wrapping/_version.py
wrapping/box_extension.py
wrapping/decorators.py
wrapping/extender.py
wrapping/importer.py
wrapping/wrappers.py
wrapping/extended/__init__.py
wrapping-0.0.3.dist-info/LICENSE
wrapping-0.0.3.dist-info/METADATA
wrapping-0.0.3.dist-info/WHEEL
wrapping-0.0.3.dist-info/top_level.txt
wrapping-0.0.3.dist-info/RECORD
