Metadata-Version: 2.1
Name: wrapping
Version: 0.0.3
Summary: Python Wrapping
Home-page: https://github.com/bhgomes/wrapping
Author: Brandon Gomes
Author-email: bhgomes.github@gmail.com
License: MIT
Platform: UNKNOWN
Classifier: License :: OSI Approved :: MIT License
Classifier: Programming Language :: Python
Classifier: Programming Language :: Python :: 3
Classifier: Programming Language :: Python :: 3 :: Only
Classifier: Programming Language :: Python :: 3.5
Classifier: Programming Language :: Python :: 3.6
Classifier: Programming Language :: Python :: 3.7
Classifier: Development Status :: 1 - Planning
Requires-Python: >=3.5.0
Requires-Dist: wrapt
